spiralChronogram/__init__.py
spiralChronogram/main.py
spiralChronogram/plotting.py
spiralChronogram/utils.py
spiralChronogram-1.3.0.dist-info/LICENSE
spiralChronogram-1.3.0.dist-info/METADATA
spiralChronogram-1.3.0.dist-info/WHEEL
spiralChronogram-1.3.0.dist-info/entry_points.txt
spiralChronogram-1.3.0.dist-info/top_level.txt
spiralChronogram-1.3.0.dist-info/RECORD
