Metadata-Version: 2.1
Name: spiralChronogram
Version: 1.3.0
Summary: A package to generate various types of 2D representations of data and spiral chronograms.
Home-page: https://github.com/thushari93/Spiral_Chronogram
Author: IMSI2024
Author-email: jcevall1@asu.edu
License: CC BY-SA 4.0
Classifier: Programming Language :: Python :: 3
Classifier: Operating System :: OS Independent
Requires-Python: >=3.6
License-File: LICENSE
Requires-Dist: numpy
Requires-Dist: pandas
Requires-Dist: matplotlib
Requires-Dist: seaborn
Requires-Dist: scipy
Requires-Dist: plotly
Requires-Dist: biopython
Requires-Dist: ipython
